machinelearning/__init__.py
machinelearning/fitaline/__init__.py
machinelearning/fitaline/housing_price/__init__.py
machinelearning/fitaline/housing_price/infer.py
machinelearning/fitaline/housing_price/train.py
machinelearning/fitaline/housing_price/train_fluid.py
machinelearning/game/__init__.py
machinelearning/game/test/__init__.py
machinelearning/game/test/game.py
machinelearning/game/test/infer.py
machinelearning/game/test/mcts.py
machinelearning/game/test/test.py
machinelearning/game/test/train.py
machinelearning/game/test/_bak/__init__.py
machinelearning/game/test/_bak/mcts_alphaZero.py
machinelearning/game/test/_bak/mcts_pure.py
machinelearning/game/test/net/__init__.py
machinelearning/game/test/net/policy_value_net.py
machinelearning/game/test/net/policy_value_net_keras.py
machinelearning/game/test/net/policy_value_net_numpy.py
machinelearning/game/test/net/policy_value_net_pytorch.py
machinelearning/game/test/net/policy_value_net_tensorflow.py
machinelearning/image/__init__.py
machinelearning/image/digit/__init__.py
machinelearning/image/digit/infer.py
machinelearning/image/digit/read_mnist.py
machinelearning/image/digit/train.py
machinelearning/lib/__init__.py
machinelearning/lib/bos.py
machinelearning/lib/download_image.py
machinelearning/lib/logger.py
machinelearning/lib/resnet.py
machinelearning/lib/utils.py
machinelearning/lib/vgg.py
machinelearning/lib/pygui/ButtonClick.wav
machinelearning/lib/pygui/Demo_All_Widgets.py
machinelearning/lib/pygui/Demo_Animated_GIFs.py
machinelearning/lib/pygui/Demo_Borderless_Window.py
machinelearning/lib/pygui/Demo_Button_Click.py
machinelearning/lib/pygui/Demo_Button_States.py
machinelearning/lib/pygui/Demo_Buttons_Mac.py
machinelearning/lib/pygui/Demo_Buttons_Nice_Graphics.py
machinelearning/lib/pygui/Demo_Change_Submits_InputText.py
machinelearning/lib/pygui/Demo_Chatterbot.py
machinelearning/lib/pygui/Demo_Chatterbot_With_TTS.py
machinelearning/lib/pygui/Demo_Color.py
machinelearning/lib/pygui/Demo_Color_Names.py
piglab-0.2.5.dist-info/LICENSE
piglab-0.2.5.dist-info/METADATA
piglab-0.2.5.dist-info/WHEEL
piglab-0.2.5.dist-info/top_level.txt
piglab-0.2.5.dist-info/RECORD
